{
  "$schema": "https://json.schemastore.org/tsconfig",
  "compilerOptions": {
    "tsBuildInfoFile": "node_modules/.tsbuildinfo/src.tsbuildinfo",
    "declaration": true,
    "declarationMap": true,
    "esModuleInterop": true,
    "incremental": true,
    "isolatedModules": true,
    "lib": ["es2022", "DOM", "DOM.Iterable"],
    "moduleDetection": "force",
    "noUncheckedIndexedAccess": true,
    "resolveJsonModule": true,
    "moduleResolution": "nodenext",
    "skipLibCheck": true,
    "strict": true,
    "target": "es2022",
    "module": "nodenext",
    "composite": true
  }
}
